CHANGES.txt
LICENSE.txt
MANIFEST.in
README.rst
setup.py
django_icons_famfamfam.egg-info/PKG-INFO
django_icons_famfamfam.egg-info/SOURCES.txt
django_icons_famfamfam.egg-info/dependency_links.txt
django_icons_famfamfam.egg-info/not-zip-safe
django_icons_famfamfam.egg-info/requires.txt
django_icons_famfamfam.egg-info/top_level.txt
icons_famfamfam/__init__.py
icons_famfamfam/static/icons/accept.png
icons_famfamfam/static/icons/ad.png
icons_famfamfam/static/icons/add.png
icons_famfamfam/static/icons/ae.png
icons_famfamfam/static/icons/af.png
icons_famfamfam/static/icons/ag.png
icons_famfamfam/static/icons/ai.png
icons_famfamfam/static/icons/al.png
icons_famfamfam/static/icons/am.png
icons_famfamfam/static/icons/an.png
icons_famfamfam/static/icons/anchor.png
icons_famfamfam/static/icons/ao.png
icons_famfamfam/static/icons/application.png
icons_famfamfam/static/icons/application_add.png
icons_famfamfam/static/icons/application_cascade.png
icons_famfamfam/static/icons/application_delete.png
icons_famfamfam/static/icons/application_double.png
icons_famfamfam/static/icons/application_edit.png
icons_famfamfam/static/icons/application_error.png
icons_famfamfam/static/icons/application_form.png
icons_famfamfam/static/icons/application_form_add.png
icons_famfamfam/static/icons/application_form_delete.png
icons_famfamfam/static/icons/application_form_edit.png
icons_famfamfam/static/icons/application_form_magnify.png
icons_famfamfam/static/icons/application_get.png
icons_famfamfam/static/icons/application_go.png
icons_famfamfam/static/icons/application_home.png
icons_famfamfam/static/icons/application_key.png
icons_famfamfam/static/icons/application_lightning.png
icons_famfamfam/static/icons/application_link.png
icons_famfamfam/static/icons/application_osx.png
icons_famfamfam/static/icons/application_osx_terminal.png
icons_famfamfam/static/icons/application_put.png
icons_famfamfam/static/icons/application_side_boxes.png
icons_famfamfam/static/icons/application_side_contract.png
icons_famfamfam/static/icons/application_side_expand.png
icons_famfamfam/static/icons/application_side_list.png
icons_famfamfam/static/icons/application_side_tree.png
icons_famfamfam/static/icons/application_split.png
