Metadata-Version: 1.1
Name: django-icons-famfamfam
Version: 0.2-1
Summary: Django staticfiles with famfamfam silk and flag icon sets
Home-page: https://github.com/agafonovdmitry/django-icons-famfamfam
Author: Dmitry Agafonov
Author-email: Dmitry@Agafonov.pp.ru
License: Various, see README file
Platform: UNKNOWN
Classifier: Development Status :: 4 - Beta
Classifier: Environment :: Web Environment
Classifier: Framework :: Django
Classifier: Intended Audience :: Developers
Classifier: Natural Language :: English
Classifier: Programming Language :: Python
